{"source":{"id":"msnbc","name":"MSNBC"},"author":"MSNBC","title":"Missouri district rescinds decision to ban Toni Morrison book","description":"A suburban St.","url":"https://www.nbcnews.com/news/nbcblk/missouri-district-rescinds-decision-ban-toni-morrison-book-rcna17858","urlToImage":"https://media-cldnry.s-nbcnews.com/image/upload/t_nbcnews-fp-1200-630,f_auto,q_auto:best/rockcms/2021-10/211029-TONI-MORRISON-MB-1149-cf0915.jpg","publishedAt":"2022-02-27T15:04:11Z","content":"WENTZVILLE, Mo. A suburban St. Louis school district has reversed its earlier decision to remove a book from its school libraries in the face of criticism and a class-action lawsuit.\r\nThe Wentzville … [+1148 chars]","id":537}