{"source":{"id":"newsweek","name":"Newsweek"},"author":"Nick Mordowanec","title":"Under Russian Assault, Kharkiv Kids, Pets Huddle on Subway Station Floor","description":"Valentyna Dylova is hiding underground with hundreds of other Ukrainians, hoping for the best in a country being torn apart by Russian aggression.","url":"https://www.newsweek.com/under-russian-assault-kharkiv-kids-pets-huddle-subway-station-floor-1682495","urlToImage":"https://d.newsweek.com/en/full/1991162/kharkiv.jpg","publishedAt":"2022-02-24T23:47:59Z","content":"Valentyna Dylova feels both terrified and strong as she hears random bursts of artillery on the ground above her.\r\nThe 29-year-old Ukrainian citizen communicated with Newsweek via WhatsApp from Khark… [+4133 chars]","id":76}