{"source":{"id":"cnn","name":"CNN"},"author":"Analysis by Nathan Hodge and Tara John, CNN","title":"Annexations, a rump state or puppet rulers. Here's what Putin may be planning for Ukraine","description":"Putin has been very clear about his basic goals in invading: He wants to disarm Ukraine, sever its ties to the NATO military alliance and end the Ukrainian people's aspirations of joining the West. Guessing exactly how he plans to execute that plan is a diffe…","url":"http://us.cnn.com/2022/02/25/europe/ukraine-russia-putin-endgame-intl/index.html","urlToImage":"https://cdn.cnn.com/cnnnext/dam/assets/220224015328-vladimir-putin-russia-address-invasion-super-tease.jpg","publishedAt":"2022-02-25T17:58:56Z","content":null,"id":211}