{"source":{"id":"bbc-news","name":"BBC News"},"author":"BBC News","title":"Asian shares rise as investors assess Ukraine war","description":"Tokyo's Nikkei 225 index opened 0.9% higher and other regional indexes were in the green.","url":"http://www.bbc.co.uk/news/business-60518578","urlToImage":"https://ichef.bbci.co.uk/news/1024/branded_news/DBF7/production/_123411365_gettyimages-1233256862.jpg","publishedAt":"2022-02-25T03:22:23.8766298Z","content":"Image source, Getty Images\r\nAsian shares have edged higher on Friday, driven by a US rebound as more sanctions were announced against Russia for its actions in Ukraine. \r\nUS President Joe Biden hit R… [+1924 chars]","id":25}