{"source":{"id":"bbc-news","name":"BBC News"},"author":"BBC News","title":"Praggnanandhaa: How India is emerging as a chess powerhouse","description":"Praggnanandhaa is the third Indian to beat world champion Magnus Carlsen in a tournament.","url":"http://www.bbc.co.uk/news/world-asia-india-60497243","urlToImage":"https://ichef.bbci.co.uk/news/1024/branded_news/143DC/production/_123380928_mediaitem123380927.jpg","publishedAt":"2022-02-25T12:52:22.0184841Z","content":"Soutik BiswasIndia correspondent\r\nImage source, R Praggnanandhaa \r\nImage caption, In 2018 Praggnanandhaa became the youngest International Master in the history of the game\r\n\"I just want to hit the b… [+7019 chars]","id":196}