{"source":{"id":"cnn","name":"CNN"},"author":"Ramishah Maruf, CNN","title":"Snapchat launches a real-time location sharing feature - CNN","description":"Snapchat on Friday announced a buddy system-like feature that allows its users to share their real-time location with friends for a period of time.","url":"https://www.cnn.com/2022/02/19/tech/snapchat-live-location-feature/index.html","urlToImage":"https://cdn.cnn.com/cnnnext/dam/assets/220219144253-snapchat-live-location-feature-super-tease.jpg","publishedAt":"2022-02-19T22:26:00Z","content":null}