{"source":{"id":"fox-news","name":"Fox News"},"author":"Fox News","title":"Tucker: How will this conflict affect you?","description":"'Tucker Carlson Tonight' host weighs in on the Biden admin's foreign policy response to the Russia-Ukraine crisis.","url":"https://video.foxnews.com/v/6298540966001/","urlToImage":"https://cf-images.us-east-1.prod.boltdns.net/v1/static/694940094001/bdc7bc58-fe69-4b11-a3b0-40e4ab34dfa1/fe504da4-c2e8-40d9-b024-c8a5673a2e0d/1280x720/match/image.jpg","publishedAt":"2022-02-23T02:07:17.6713817Z","content":null}