{"source":{"id":"cnn","name":"CNN"},"author":null,"title":"Michael Smerconish: When is it war?  - CNN Video","description":"America's reluctance to get directly involved with Poland's transfer of planes to Ukraine raises the question: What's the \"trip wire\" that Putin would view as America being at war with Russia?","url":"http://us.cnn.com/videos/world/2022/03/12/smerconish-when-is-it-war.cnn","urlToImage":"https://cdn.cnn.com/cnnnext/dam/assets/220312093611-smerconish-3-12-2022-super-tease.jpg","publishedAt":"2022-03-12T15:07:35.7445282Z","content":null,"id":563}