{"source":{"id":"cnn","name":"CNN"},"author":null,"title":"War in Ukraine: CNN military analyst on what Russia will do next - CNN Video","description":"CNN military analyst retired Col. Cedric Leighton breaks down Russia's attacks on Ukraine and what he believes will come next.","url":"http://us.cnn.com/videos/world/2022/02/24/russia-ukraine-invasion-military-leighton-magic-wall-nr-vpx.cnn","urlToImage":"https://cdn.cnn.com/cnnnext/dam/assets/220224153025-col-cedric-leighton-vpx-super-tease.jpg","publishedAt":"2022-02-24T21:22:27.3757979Z","content":null,"id":98}